{
  "hash": "f214aa52",
  "configHash": "6a78740d",
  "lockfileHash": "4ada577d",
  "browserHash": "4109efcd",
  "optimized": {
    "react": {
      "src": "../../node_modules/react/index.js",
      "file": "react.js",
      "fileHash": "ddd04284",
      "needsInterop": true
    },
    "react-dom/client": {
      "src": "../../node_modules/react-dom/client.js",
      "file": "react-dom_client.js",
      "fileHash": "df793824",
      "needsInterop": true
    }
  },
  "chunks": {
    "chunk-GFWMZNU4": {
      "file": "chunk-GFWMZNU4.js"
    }
  }
}